repath.py
repath-0.9.0.dist-info/LICENSE
repath-0.9.0.dist-info/METADATA
repath-0.9.0.dist-info/WHEEL
repath-0.9.0.dist-info/top_level.txt
repath-0.9.0.dist-info/RECORD
